elevenlabs_s3/__init__.py
elevenlabs_s3/elevenlabs_s3.py
elevenlabs_s3-0.3.2.dist-info/METADATA
elevenlabs_s3-0.3.2.dist-info/WHEEL
elevenlabs_s3-0.3.2.dist-info/RECORD
