Metadata-Version: 2.1
Name: elevenlabs-s3
Version: 0.3.2
Summary: A package that combines ElevenLabs TTS and AWS S3 upload.
Author: Andy
Author-email: andychert@protonmail.com
Requires-Python: >=3.8,<4.0
Classifier: Programming Language :: Python :: 3
Classifier: Programming Language :: Python :: 3.8
Classifier: Programming Language :: Python :: 3.9
Classifier: Programming Language :: Python :: 3.10
Classifier: Programming Language :: Python :: 3.11
Classifier: Programming Language :: Python :: 3.12
Classifier: Programming Language :: Python :: 3.13
Requires-Dist: boto3 (>=1.35.36,<2.0.0)
Requires-Dist: elevenlabs (>=1.9.0,<2.0.0)
Requires-Dist: requests (>=2.32.3,<3.0.0)
